packthing/__init__.py
packthing/icons.py
packthing/importer.py
packthing/main.py
packthing/util.py
packthing/builders/__init__.py
packthing/builders/base.py
packthing/builders/dir.py
packthing/builders/fpc.py
packthing/builders/prebuilt.py
packthing/builders/qmake.py
packthing/packagers/__init__.py
packthing/packagers/_base.py
packthing/packagers/_linux.py
packthing/packagers/deb.py
packthing/packagers/dmg.py
packthing/packagers/inno.py
packthing/packagers/run.py
packthing/template/deb/changelog
packthing/template/deb/compat
packthing/template/deb/control
packthing/template/deb/desktop
packthing/template/deb/menu
packthing/template/deb/package.mime
packthing/template/deb/package.sharedmimeinfo.body
packthing/template/deb/package.sharedmimeinfo.footer
packthing/template/deb/package.sharedmimeinfo.header
packthing/template/deb/postinst
packthing/template/dmg/dmgbuild.py
packthing/template/dmg/install.AppleScript
packthing/template/dmg/installer.AppleScript
packthing/template/inno/file.iss
packthing/template/inno/mime.iss
packthing/template/inno/run.iss
packthing/template/inno/setup.iss
packthing/template/run/self_extracting.sh
packthing/template/run/setup.sh
packthing/vcs/__init__.py
packthing/vcs/base.py
packthing/vcs/git.py
packthing-1.2.0.dist-info/LICENSE
packthing-1.2.0.dist-info/METADATA
packthing-1.2.0.dist-info/WHEEL
packthing-1.2.0.dist-info/entry_points.txt
packthing-1.2.0.dist-info/top_level.txt
packthing-1.2.0.dist-info/RECORD
