Metadata-Version: 2.1
Name: packthing
Version: 1.2.0
Summary: Write once, package everywhere
Home-page: https://github.com/lamestation/packthing
Author: LameStation
Author-email: contact@lamestation.com
License: GPLv3
Keywords: packaging qt qmake building distribution
Platform: UNKNOWN
Classifier: Environment :: Console
Classifier: Development Status :: 2 - Pre-Alpha
Classifier: License :: OSI Approved :: GNU General Public License v3 (GPLv3)
Classifier: Programming Language :: Python :: 3.6
Classifier: Programming Language :: Python :: 3.7
Classifier: Programming Language :: Python :: 3.8
Classifier: Topic :: Software Development :: Code Generators
Classifier: Topic :: System :: Archiving :: Packaging
Classifier: Topic :: Utilities
Requires-Dist: pyyaml
Requires-Dist: dmgbuild ; sys_platform == "darwin"
